Metadata-Version: 2.1
Name: FullMeanAveragePrecision
Version: 1.3
Summary: Expanded version MeanAveragePrecision metric torchmetrics library
Author: Vlad Efremov
Author-email: efremov.va@phystech.edu
Requires-Dist: torch
Requires-Dist: torchmetrics
Requires-Dist: pycocotools
